aws/osml/model_runner/__init__.py
aws/osml/model_runner/app_config.py
aws/osml/model_runner/exceptions.py
aws/osml/model_runner/image_request_handler.py
aws/osml/model_runner/model_runner.py
aws/osml/model_runner/region_request_handler.py
aws/osml/model_runner/api/__init__.py
aws/osml/model_runner/api/exceptions.py
aws/osml/model_runner/api/image_request.py
aws/osml/model_runner/api/inference.py
aws/osml/model_runner/api/region_request.py
aws/osml/model_runner/api/request_utils.py
aws/osml/model_runner/api/sink.py
aws/osml/model_runner/common/__init__.py
aws/osml/model_runner/common/auto_string_enum.py
aws/osml/model_runner/common/credentials_utils.py
aws/osml/model_runner/common/endpoint_utils.py
aws/osml/model_runner/common/exceptions.py
aws/osml/model_runner/common/feature_utils.py
aws/osml/model_runner/common/log_context.py
aws/osml/model_runner/common/mr_post_processing.py
aws/osml/model_runner/common/timer.py
aws/osml/model_runner/common/typing.py
aws/osml/model_runner/database/__init__.py
aws/osml/model_runner/database/ddb_helper.py
aws/osml/model_runner/database/endpoint_statistics_table.py
aws/osml/model_runner/database/exceptions.py
aws/osml/model_runner/database/feature_table.py
aws/osml/model_runner/database/job_table.py
aws/osml/model_runner/database/region_request_table.py
aws/osml/model_runner/inference/__init__.py
aws/osml/model_runner/inference/detector.py
aws/osml/model_runner/inference/endpoint_builder.py
aws/osml/model_runner/inference/endpoint_factory.py
aws/osml/model_runner/inference/exceptions.py
aws/osml/model_runner/inference/feature_selection.py
aws/osml/model_runner/inference/feature_utils.py
aws/osml/model_runner/inference/http_detector.py
aws/osml/model_runner/inference/sm_detector.py
aws/osml/model_runner/queue/__init__.py
aws/osml/model_runner/queue/request_queue.py
aws/osml/model_runner/sink/__init__.py
aws/osml/model_runner/sink/exceptions.py
aws/osml/model_runner/sink/kinesis_sink.py
aws/osml/model_runner/sink/s3_sink.py
osml_model_runner-2.3.0.dist-info/LICENSE
osml_model_runner-2.3.0.dist-info/METADATA
osml_model_runner-2.3.0.dist-info/WHEEL
osml_model_runner-2.3.0.dist-info/top_level.txt
osml_model_runner-2.3.0.dist-info/RECORD
