Metadata-Version: 2.1
Name: osml-model-runner
Version: 2.3.0
Summary: Application to run large scale imagery against AI/ML models
Author: Amazon Web Services
Author-email: aws-osml-admin@amazon.com
License: 
Project-URL: Source, https://github.com/aws-solutions-library-samples/osml-model-runner
Project-URL: Tracker, https://github.com/aws-solutions-library-samples/osml-model-runner/issues
Classifier: Programming Language :: Python :: 3
Classifier: Operating System :: OS Independent
Requires-Python: >=3.8
License-File: LICENSE
Requires-Dist: osml-imagery-toolkit>=1.3.0
Requires-Dist: numpy>=1.24.4
Requires-Dist: shapely>=2.0.2
Requires-Dist: aws-embedded-metrics==3.2.0
Requires-Dist: python-json-logger>=2.0.0
Requires-Dist: boto3==1.34.28
Requires-Dist: botocore==1.34.28
Requires-Dist: setuptools==69.0.3
Requires-Dist: cachetools==5.3.2
Requires-Dist: geojson>=3.1.0
Requires-Dist: scikit-optimize>=0.9.0
Requires-Dist: pyproj>=3.6.1
Requires-Dist: scipy==1.9.1; python_version < "3.11.0"
Requires-Dist: scipy==1.12.0; python_version >= "3.11"
Requires-Dist: argparse==1.4.0
Requires-Dist: dacite==1.8.1
Requires-Dist: ensemble-boxes==1.0.9
Requires-Dist: codeguru-profiler-agent==1.2.4
Requires-Dist: defusedxml>=0.7.1
Requires-Dist: requests==2.31.0
Provides-Extra: gdal
Requires-Dist: gdal>=3.8.3; extra == "gdal"
Provides-Extra: test
Requires-Dist: tox; extra == "test"
